tmdb/__init__.py
tmdb/tests/__init__.py
tmdb/tests/test_tmdb_api.py
tmdb/tests/test_tmdb_entry.py
tmdb/tests/test_tmdb_request.py
themoviedb_lib-0.0.5.dist-info/LICENSE
themoviedb_lib-0.0.5.dist-info/METADATA
themoviedb_lib-0.0.5.dist-info/WHEEL
themoviedb_lib-0.0.5.dist-info/top_level.txt
themoviedb_lib-0.0.5.dist-info/RECORD
