Metadata-Version: 2.1
Name: themoviedb-lib
Version: 0.0.5
Summary: Library providing useful tools for The Movie Database (TMDb). Not dependent on API-keys.
Home-page: https://github.com/inwerk/themoviedb-lib
Author: 
Author-email: 
Keywords: tmdb,themoviedb,the movie database,the movie db,movie,movies,tv,tv show,tv shows
Classifier: Development Status :: 2 - Pre-Alpha
Classifier: Intended Audience :: Developers
Classifier: License :: OSI Approved :: MIT License
Classifier: Programming Language :: Python :: 3
Classifier: Programming Language :: Python :: 3.11
Classifier: Topic :: Software Development :: Build Tools
License-File: LICENSE
Requires-Dist: requests
Requires-Dist: beautifulsoup4
Requires-Dist: fake-useragent
